<?xml version="1.0"?>
<!-- This file is part of the sale_payment module for Tryton.
The COPYRIGHT file at the top level of this repository contains the full
copyright notices and license terms. -->
<tryton>
    <data>

        <record model="res.group" id="group_move_force">
            <field name="name">Nodux - Editar Asientos Contables</field>
        </record>

        <record model="res.user-res.group"
            id="user_admin_group_move_force">
            <field name="user" ref="res.user_admin"/>
            <field name="group" ref="group_move_force"/>
        </record>

        <record model="res.user-res.group"
            id="user_trigger_group_move_force">
            <field name="user" ref="res.user_admin"/>
            <field name="group" ref="group_move_force"/>
        </record>


    </data>
</tryton>
